README.md
setup.cfg
setup.py
ppa6/__init__.py
ppa6/__main__.py
ppa6.egg-info/PKG-INFO
ppa6.egg-info/SOURCES.txt
ppa6.egg-info/dependency_links.txt
ppa6.egg-info/entry_points.txt
ppa6.egg-info/requires.txt
ppa6.egg-info/top_level.txt