Metadata-Version: 1.1
Name: ppa6
Version: 0.2
Summary: Utility for printing on Peripage A6/A6+ via bluetooth
Home-page: https://github.com/bitrate16/ppa6-python
Author: bitrate16
Author-email: bitrate16@gmail.com
License: MIT
Download-URL: https://github.com/bitrate16/ppa6-python/archive/v0.2.tar.gz
Keywords: PERIPAGE,BLUETOOTH,THERMAL PRINTER,PRINTER
Platform: UNKNOWN
Classifier: Development Status :: 4 - Beta
Classifier: Intended Audience :: Developers
Classifier: Topic :: Software Development :: Libraries :: Python Modules
Classifier: License :: OSI Approved :: MIT License
Classifier: Programming Language :: Python :: 3
Classifier: Programming Language :: Python :: 3.6
Classifier: Programming Language :: Python :: 3.7
Classifier: Programming Language :: Python :: 3.8
